[[{"mon": "Sylveon", "usage": 29.07859, "type1": "fairy", "type2": "none"}, {"mon": "Landorus-Therian", "usage": 25.61656, "type1": "ground", "type2": "flying"}, {"mon": "Kangaskhan", "usage": 25.11271, "type1": "normal", "type2": "none"}, {"mon": "Bisharp", "usage": 21.92506, "type1": "dark", "type2": "steel"}, {"mon": "Talonflame", "usage": 19.36453, "type1": "flying", "type2": "fire"}, {"mon": "Thundurus", "usage": 17.00259, "type1": "electric", "type2": "flying"}, {"mon": "Heatran", "usage": 15.57915, "type1": "fire", "type2": "steel"}, {"mon": "Salamence", "usage": 15.33044, "type1": "dragon", "type2": "flying"}, {"mon": "Rotom-Wash", "usage": 15.01062, "type1": "electric", "type2": "water"}, {"mon": "Aegislash", "usage": 14.12405, "type1": "ghost", "type2": "steel"}, {"mon": "Charizard", "usage": 13.52290, "type1": "fire", "type2": "flying"}, {"mon": "Amoonguss", "usage": 13.38240, "type1": "grass", "type2": "poison"}, {"mon": "Terrakion", "usage": 12.71821, "type1": "rock", "type2": "fighting"}, {"mon": "Cresselia", "usage": 11.75520, "type1": "psychic", "type2": "none"}, {"mon": "Gengar", "usage": 11.38701, "type1": "ghost", "type2": "poison"}, {"mon": "Milotic", "usage": 10.99007, "type1": "water", "type2": "none"}, {"mon": "Hydreigon", "usage": 10.36382, "type1": "dragon", "type2": "dark"}, {"mon": "Garchomp", "usage": 9.70552, "type1": "dragon", "type2": "ground"}, {"mon": "Zapdos", "usage": 9.14813, "type1": "electric", "type2": "flying"}, {"mon": "Metagross", "usage": 9.05345, "type1": "steel", "type2": "psychic"}],
[{ "mon": "Landorus-Therian", "usage": 24.66462, "type1": "ground", "type2": "flying"}, { "mon": "Kangaskhan", "usage": 22.56100, "type1": "normal", "type2": "none"}, {"mon": "Sylveon", "usage": 21.89532, "type1": "fairy", "type2": "none"}, {"mon": "Bisharp", "usage": 20.65715, "type1": "dark", "type2": "steel"}, {"mon": "Terrakion", "usage": 18.92378, "type1": "rock", "type2": "fighting"}, {"mon": "Heatran", "usage": 18.33724, "type1": "fire", "type2": "steel"}, {"mon": "Thundurus", "usage": 18.21484, "type1": "electric", "type2": "flying"}, {"mon": "Talonflame", "usage": 17.66474, "type1": "fire", "type2": "flying"}, {"mon": "Gengar", "usage": 17.16991, "type1": "ghost", "type2": "poison"}, {"mon": "Suicune", "usage": 15.50523, "type1": "water", "type2": "none"}, {"mon": "Amoonguss", "usage": 14.51690, "type1": "grass", "type2": "poison"}, {"mon": "Charizard", "usage": 13.48776, "type1": "fire", "type2": "flying"}, {"mon": "Salamence", "usage": 12.78065, "type1": "dragon", "type2": "flying"}, {"mon": "Aegislash", "usage": 12.58693, "type1": "ghost", "type2": "steel"}, {"mon": "Rotom-Wash", "usage": 12.55665, "type1": "electric", "type2": "water"}, {"mon": "Cresselia", "usage": 11.66095, "type1": "psychic", "type2": "none"}, {"mon": "Hydreigon", "usage": 10.28151, "type1": "dragon", "type2": "dark"}, {"mon": "Zapdos", "usage": 9.98115, "type1": "electric", "type2": "flying"}, {"mon": "Venusaur", "usage": 9.66248, "type1": "grass", "type2": "poison"}, {"mon": "Metagross", "usage": 9.54844, "type1": "steel", "type2": "psychic"}],
[{ "mon": "Landorus-Therian", "usage": 30.27183, "type1": "ground", "type2": "flying"}, {"mon": "Kangaskhan", "usage": 23.916030, "type1": "normal", "type2": "none"}, { "mon": "Sylveon", "usage": 21.10251, "type1": "fairy", "type2": "none"}, {"mon": "Thundurus", "usage": 19.06848, "type1": "electric", "type2": "flying"}, {"mon": "Heatran", "usage": 18.87843, "type1": "fire", "type2": "steel"}, {"mon": "Bisharp", "usage": 17.56921, "type1": "dark", "type2": "steel"}, {"mon": "Terrakion", "usage": 17.33698, "type1": "rock", "type2": "fighting"}, {"mon": "Talonflame", "usage": 17.27399, "type1": "fire", "type2": "flying"}, {"mon": "Aegislash", "usage": 15.90218, "type1": "ghost", "type2": "steel"}, {"mon": "Gengar", "usage": 14.39197, "type1": "ghost", "type2": "poison"}, {"mon": "Hydreigon", "usage": 14.30305, "type1": "dragon", "type2": "dark"}, {"mon": "Suicune", "usage": 14.02717, "type1": "water", "type2": "none"}, {"mon": "Rotom-Wash", "usage": 13.81297, "type1": "electric", "type2": "water"}, {"mon": "Amoonguss", "usage": 13.72421, "type1": "grass", "type2": "poison"}, {"mon": "Cresselia", "usage": 12.63738, "type1": "psychic", "type2": "none"}, {"mon": "Charizard", "usage": 12.02888, "type1": "fire", "type2": "flying"}, {"mon": "Metagross", "usage": 11.05494, "type1": "psychic", "type2": "steel"}, {"mon": "Zapdos", "usage": 11.01885, "type1": "electric", "type2": "flying"}, {"mon": "Salamence", "usage": 10.88349, "type1": "dragon", "type2": "flying"}, {"mon": "Conkeldurr", "usage": 10.34182, "type1": "fighting", "type2": "none"}],
[{ "mon": "Landorus-Therian", "usage": 29.45742, "type1": "ground", "type2": "flying"}, {"mon": "Kangaskhan", "usage": 24.43702, "type1": "normal", "type2": "none"}, {"mon": "Thundurus", "usage": 21.42776, "type1": "electric", "type2": "flying"}, { "mon": "Heatran", "usage": 20.96625, "type1": "fire", "type2": "steel"}, {"mon": "Sylveon", "usage": 20.30770, "type1": "fairy", "type2": "none"}, {"mon": "Terrakion", "usage": 17.81610, "type1": "rock", "type2": "fighting"}, {"mon": "Talonflame", "usage": 16.60551, "type1": "fire", "type2": "flying"}, {"mon": "Aegislash", "usage": 15.87015, "type1": "ghost", "type2": "steel"}, {"mon": "Bisharp", "usage": 15.55195, "type1": "dark", "type2": "steel"}, {"mon": "Amoonguss", "usage": 14.78265, "type1": "grass", "type2": "poison"}, {"mon": "Hydreigon", "usage": 14.62312, "type1": "dragon", "type2": "dark"}, {"mon": "Suicune", "usage": 14.46536, "type1": "water", "type2": "none"}, {"mon": "Gengar", "usage": 12.49898, "type1": "ghost", "type2": "poison"}, {"mon": "Charizard", "usage": 12.27558, "type1": "fire", "type2": "flying"}, {"mon": "Cresselia", "usage": 12.06507, "type1": "psychic", "type2": "none"}, {"mon": "Metagross", "usage": 11.45351, "type1": "steel", "type2": "psychic"}, {"mon": "Rotom-Wash", "usage": 11.32981, "type1": "electric", "type2": "water"}, {"mon": "Salamence", "usage": 10.87092, "type1": "dragon", "type2": "flying"}, {"mon": "Zapdos", "usage": 10.16474, "type1": "electric", "type2": "flying"}, {"mon": "Breloom", "usage": 9.93374, "type1": "grass", "type2": "fighting"}],
[{ "mon": "Landorus-Therian", "usage": 31.57166, "type1": "ground", "type2": "flying"}, {"mon": "Kangaskhan", "usage": 23.28726, "type1": "normal", "type2": "none"}, {"mon": "Thundurus", "usage": 22.12487, "type1": "electric", "type2": "flying"}, {"mon": "Heatran", "usage": 21.17350, "type1": "fire", "type2": "steel"}, {"mon": "Aegislash", "usage": 18.19669, "type1": "ghost", "type2": "steel"}, { "mon": "Amoonguss", "usage": 17.84484, "type1": "grass", "type2": "poison"}, {"mon": "Sylveon", "usage": 17.41552, "type1": "fairy", "type2": "none"}, {"mon": "Terrakion", "usage": 15.22264, "type1": "rock", "type2": "fighting"}, {"mon": "Talonflame", "usage": 14.75363, "type1": "fire", "type2": "flying"}, {"mon": "Bisharp", "usage": 14.15791, "type1": "dark", "type2": "steel"}, {"mon": "Hydreigon", "usage": 13.86491, "type1": "dragon", "type2": "dark"}, {"mon": "Suicune", "usage": 13.32533, "type1": "water", "type2": "none"}, {"mon": "Charizard", "usage": 13.13604, "type1": "fire", "type2": "flying"}, {"mon": "Salamence", "usage": 13.11871, "type1": "dragon", "type2": "flying"}, {"mon": "Rotom-Wash", "usage": 12.58649, "type1": "electric", "type2": "water"}, {"mon": "Gengar", "usage": 11.22237, "type1": "ghost", "type2": "poison"}, {"mon": "Cresselia", "usage": 11.18502, "type1": "psychic", "type2": "none"}, {"mon": "Metagross", "usage": 10.13469, "type1": "steel", "type2": "psychic"}, {"mon": "Gardevoir", "usage": 9.96928, "type1": "psychic", "type2": "fairy"}, {"mon": "Venusaur", "usage": 9.54900, "type1": "grass", "type2": "poison"}],
[{ "mon": "Landorus-Therian", "usage": 33.87741, "type1": "ground", "type2": "flying"}, {"mon": "Kangaskhan", "usage": 25.25638, "type1": "normal", "type2": "none"}, {"mon": "Thundurus", "usage": 23.03047, "type1": "electric", "type2": "flying"}, {"mon": "Amoonguss", "usage": 22.18536, "type1": "grass", "type2": "poison"}, {"mon": "Heatran", "usage": 22.04379, "type1": "fire", "type2": "steel"}, {"mon": "Aegislash", "usage": 21.54028, "type1": "ghost", "type2": "steel"}, { "mon": "Sylveon", "usage": 17.47430, "type1": "fairy", "type2": "none"}, {"mon": "Salamence", "usage": 14.86558, "type1": "dragon", "type2": "flying"}, {"mon": "Rotom-Wash", "usage": 13.13278, "type1": "electric", "type2": "water"}, {"mon": "Talonflame", "usage": 12.95830, "type1": "fire", "type2": "flying"}, {"mon": "Milotic", "usage": 12.65302, "type1": "water", "type2": "none"}, {"mon": "Charizard", "usage": 12.46277, "type1": "fire", "type2": "flying"}, {"mon": "Cresselia", "usage": 12.37746, "type1": "psychic", "type2": "none"}, {"mon": "Terrakion", "usage": 12.08887, "type1": "rock", "type2": "fighting"}, {"mon": "Bisharp", "usage": 11.83888, "type1": "dark", "type2": "steel"}, {"mon": "Gardevoir", "usage": 11.59491, "type1": "psychic", "type2": "fairy"}, {"mon": "Gengar", "usage": 10.60969, "type1": "ghost", "type2": "poison"}, {"mon": "Hydreigon", "usage": 10.31553, "type1": "dragon", "type2": "dark"}, {"mon": "Scrafty", "usage": 9.82863, "type1": "fighting", "type2": "dark"}, {"mon": "Suicune", "usage": 9.64813, "type1": "water", "type2": "none"}],
[{ "mon": "Landorus-Therian", "usage": 33.18686, "type1": "ground", "type2": "flying"}, {"mon": "Amoonguss", "usage": 25.16840, "type1": "grass", "type2": "poison"}, {"mon": "Thundurus", "usage": 23.74529, "type1": "electric", "type2": "flying"}, {"mon": "Aegislash", "usage": 23.29667, "type1": "ghost", "type2": "steel"}, {"mon": "Kangaskhan", "usage": 22.08078, "type1": "normal", "type2": "none"}, {"mon": "Heatran", "usage": 21.99949, "type1": "fire", "type2": "steel"}, {"mon": "Sylveon", "usage": 17.14234, "type1": "fairy", "type2": "none"}, {"mon": "Milotic", "usage": 17.12792, "type1": "water", "type2": "none"}, {"mon": "Salamence", "usage": 15.70661, "type1": "dragon", "type2": "flying"}, {"mon": "Gardevoir", "usage": 13.85985, "type1": "psychic", "type2": "fairy"}, {"mon": "Rotom-Wash", "usage": 13.42756, "type1": "electric", "type2": "water"}, {"mon": "Charizard", "usage": 12.66877, "type1": "fire", "type2": "flying"}, {"mon": "Bisharp", "usage": 11.75286, "type1": "dark", "type2": "steel"}, {"mon": "Tyranitar", "usage": 11.13655, "type1": "dark", "type2": "rock"}, {"mon": "Cresselia", "usage": 10.92742, "type1": "psychic", "type2": "none"}, {"mon": "Gengar", "usage": 10.82995, "type1": "ghost", "type2": "poison"}, {"mon": "Talonflame", "usage": 10.73067, "type1": "fire", "type2": "flying"}, {"mon": "Politoed", "usage": 10.33426, "type1": "water", "type2": "none"}, {"mon": "Hydreigon", "usage": 9.70964, "type1": "dragon", "type2": "dark"}, {"mon": "Scrafty", "usage": 9.68644, "type1": "fighting", "type2": "dark"}],
[{ "mon": "Landorus-Therian", "usage": 36.48988, "type1": "ground", "type2": "flying"}, {"mon": "Thundurus", "usage": 25.74127, "type1": "electric", "type2": "flying"}, {"mon": "Kangaskhan", "usage": 23.95734, "type1": "normal", "type2": "none"}, {"mon": "Aegislash", "usage": 23.45892, "type1": "ghost", "type2": "steel"}, {"mon": "Amoonguss", "usage": 22.87184, "type1": "grass", "type2": "poison"}, {"mon": "Heatran", "usage": 22.53232, "type1": "fire", "type2": "steel"}, { "mon": "Sylveon", "usage": 17.21635, "type1": "fairy", "type2": "none"}, {"mon": "Milotic", "usage": 16.56490, "type1": "water", "type2": "none"}, {"mon": "Salamence", "usage": 14.45957, "type1": "dragon", "type2": "flying"}, {"mon": "Charizard", "usage": 14.31076, "type1": "fire", "type2": "flying"}, {"mon": "Gardevoir", "usage": 13.96872, "type1": "psychic", "type2": "fairy"}, {"mon": "Cresselia", "usage": 13.44566, "type1": "psychic", "type2": "none"}, {"mon": "Rotom-Wash", "usage": 11.37951, "type1": "electric", "type2": "water"}, {"mon": "Tyranitar", "usage": 10.37983, "type1": "dark", "type2": "rock"}, {"mon": "Conkeldurr", "usage": 10.14207, "type1": "fighting", "type2": "none"}, {"mon": "Bisharp", "usage": 10.10988, "type1": "dark", "type2": "steel"}, {"mon": "Gengar", "usage": 10.07791, "type1": "ghost", "type2": "poison"}, {"mon": "Politoed", "usage": 9.80458, "type1": "water", "type2": "none"}, {"mon": "Talonflame", "usage": 9.72068, "type1": "fire", "type2": "flying"}, {"mon": "Zapdos", "usage": 8.66833, "type1": "electric", "type2": "flying"}],
[{ "mon": "Landorus-Therian", "usage": 39.35961, "type1": "ground", "type2": "flying"}, {"mon": "Thundurus", "usage": 29.08698, "type1": "electric", "type2": "flying"}, {"mon": "Kangaskhan", "usage": 27.69648, "type1": "normal", "type2": "none"}, {"mon": "Heatran", "usage": 24.29106, "type1": "fire", "type2": "steel"}, {"mon": "Amoonguss", "usage": 23.02854, "type1": "grass", "type2": "poison"}, {"mon": "Aegislash", "usage": 22.68007, "type1": "ghost", "type2": "steel"}, { "mon": "Sylveon", "usage": 17.39772, "type1": "fairy", "type2": "none"}, {"mon": "Cresselia", "usage": 16.98199, "type1": "psychic", "type2": "none"}, {"mon": "Milotic", "usage": 14.98448, "type1": "water", "type2": "none"}, {"mon": "Charizard", "usage": 13.55171, "type1": "fire", "type2": "flying"}, {"mon": "Salamence", "usage": 13.24849, "type1": "dragon", "type2": "flying"}, {"mon": "Gardevoir", "usage": 12.69790, "type1": "psychic", "type2": "fairy"}, {"mon": "Rotom-Wash", "usage": 10.02049, "type1": "electric", "type2": "water"}, {"mon": "Gengar", "usage": 9.92463, "type1": "ghost", "type2": "poison"}, {"mon": "Talonflame", "usage": 9.59553, "type1": "fire", "type2": "flying"}, {"mon": "Tyranitar", "usage": 9.52649, "type1": "rock", "type2": "dark"}, {"mon": "Conkeldurr", "usage": 9.48690, "type1": "fighting", "type2": "none"}, {"mon": "Bisharp", "usage": 9.29637, "type1": "dark", "type2": "steel"}, {"mon": "Politoed", "usage": 9.02043, "type1": "water", "type2": "none"}, {"mon": "Scrafty", "usage": 8.26705, "type1": "fighting", "type2": "dark"}],
[{ "mon": "Landorus-Therian", "usage": 38.54729, "type1": "ground", "type2": "flying"}, {"mon": "Thundurus", "usage": 28.75847, "type1": "electric", "type2": "flying"}, {"mon": "Kangaskhan", "usage": 27.92421, "type1": "normal", "type2": "none"}, {"mon": "Amoonguss", "usage": 22.83325, "type1": "grass", "type2": "poison"}, {"mon": "Aegislash", "usage": 22.73384, "type1": "ghost", "type2": "steel"}, {"mon": "Heatran", "usage": 22.57441, "type1": "fire", "type2": "steel"}, { "mon": "Cresselia", "usage": 17.99941, "type1": "psychic", "type2": "none"}, {"mon": "Sylveon", "usage": 17.80900, "type1": "fairy", "type2": "none"}, {"mon": "Milotic", "usage": 15.02136, "type1": "water", "type2": "none"}, {"mon": "Charizard", "usage": 14.21616, "type1": "fire", "type2": "flying"}, {"mon": "Salamence", "usage": 13.41978, "type1": "dragon", "type2": "flying"}, {"mon": "Gardevoir", "usage": 12.09929, "type1": "psychic", "type2": "fairy"}, {"mon": "Talonflame", "usage": 10.70003, "type1": "fire", "type2": "flying"}, {"mon": "Politoed", "usage": 9.75018, "type1": "water", "type2": "none"}, {"mon": "Tyranitar", "usage": 9.70561, "type1": "dark", "type2": "rock"}, {"mon": "Rotom-Wash", "usage": 9.41550, "type1": "electric", "type2": "water"}, {"mon": "Conkeldurr", "usage": 9.00079, "type1": "fighting", "type2": "none"}, {"mon": "Gengar", "usage": 8.63873, "type1": "ghost", "type2": "poison"}, {"mon": "Bisharp", "usage": 8.49376, "type1": "dark", "type2": "steel"}, {"mon": "Azumarill", "usage": 8.26230, "type1": "water", "type2": "fairy"}],
[{ "mon": "Landorus-Therian", "usage": 37.04463, "type1": "ground", "type2": "flying"}, {"mon": "Kangaskhan-Mega", "usage": 27.39968, "type1": "normal", "type2": "none"}, {"mon": "Thundurus", "usage": 27.28828, "type1": "electric", "type2": "flying"}, {"mon": "Amoonguss", "usage": 23.98377, "type1": "grass", "type2": "poison"}, {"mon": "Heatran", "usage": 23.45882, "type1": "fire", "type2": "steel"}, {"mon": "Aegislash", "usage": 21.39322, "type1": "ghost", "type2": "steel"}, { "mon": "Sylveon", "usage": 17.35393, "type1": "fairy", "type2": "none"}, {"mon": "Cresselia", "usage": 16.14618, "type1": "psychic", "type2": "none"}, {"mon": "Milotic", "usage": 15.90277, "type1": "water", "type2": "none"}, {"mon": "Salamence-Mega", "usage": 14.62620, "type1": "dragon", "type2": "flying"}, {"mon": "Charizard-Mega-Y", "usage": 11.74567, "type1": "fire", "type2": "flying"}, {"mon": "Gardevoir-Mega", "usage": 10.69708, "type1": "psychic", "type2": "fairy"}, {"mon": "Rotom-Wash", "usage": 9.88670, "type1": "electric", "type2": "water"}, {"mon": "Politoed", "usage": 9.78397, "type1": "water", "type2": "none"}, {"mon": "Tyranitar", "usage": 9.72416, "type1": "rock", "type2": "dark"}, {"mon": "Talonflame", "usage": 9.28392, "type1": "fire", "type2": "flying"}, {"mon": "Azumarill", "usage": 9.06858, "type1": "water", "type2": "fairy"}, {"mon": "Conkeldurr", "usage": 8.20154, "type1": "fighting", "type2": "none"}, {"mon": "Ferrothorn", "usage": 8.12413, "type1": "grass", "type2": "steel"}, {"mon": "Terrakion", "usage": 8.00532, "type1": "fighting", "type2": "rock"}],
[{ "mon": "Landorus-Therian", "usage": 37.60508, "type1": "ground", "type2": "flying"}, {"mon": "Thundurus", "usage": 27.19057, "type1": "electric", "type2": "flying"}, {"mon": "Kangaskhan-Mega", "usage": 26.01639, "type1": "normal", "type2": "none"}, {"mon": "Heatran", "usage": 22.90801, "type1": "fire", "type2": "steel"}, {"mon": "Amoonguss", "usage": 22.28327, "type1": "grass", "type2": "poison"}, {"mon": "Aegislash", "usage": 20.98517, "type1": "ghost", "type2": "steel"}, { "mon": "Sylveon", "usage": 17.40620, "type1": "fairy", "type2": "none"}, {"mon": "Cresselia", "usage": 17.15837, "type1": "psychic", "type2": "none"}, {"mon": "Milotic", "usage": 14.32236, "type1": "water", "type2": "none"}, {"mon": "Salamence-Mega", "usage": 13.73945, "type1": "dragon", "type2": "flying"}, {"mon": "Charizard-Mega-Y", "usage": 12.75437, "type1": "fire", "type2": "flying"}, {"mon": "Rotom-Wash", "usage": 10.28570, "type1": "electric", "type2": "water"}, {"mon": "Talonflame", "usage": 10.10266, "type1": "fire", "type2": "flying"}, {"mon": "Gardevoir-Mega", "usage": 10.07007, "type1": "psychic", "type2": "fairy"}, {"mon": "Politoed", "usage": 9.88921, "type1": "water", "type2": "none"}, {"mon": "Tyranitar", "usage": 9.00608, "type1": "rock", "type2": "dark"}, {"mon": "Azumarill", "usage": 8.60255, "type1": "water", "type2": "fairy"}, {"mon": "Bisharp", "usage": 8.24589, "type1": "dark", "type2": "steel"}, {"mon": "Ferrothorn", "usage": 8.06420, "type1": "grass", "type2": "steel"}, {"mon": "Terrakion", "usage": 8.02796, "type1": "rock", "type2": "fighting"}]]